multitype_file_field/__init__.py
multitype_file_field/fields.py
multitype_file_field/forms.py
multitype_file_field/utils.py
multitype_file_field/widgets.py
django_multitype_file_field-0.0.6.dist-info/LICENSE
django_multitype_file_field-0.0.6.dist-info/METADATA
django_multitype_file_field-0.0.6.dist-info/WHEEL
django_multitype_file_field-0.0.6.dist-info/top_level.txt
django_multitype_file_field-0.0.6.dist-info/RECORD
